package/DataPrep_Kit.py
package/DataPrep_Kit_khater.py
package/__init__.py
DataPrep_Kit_khater-18.12.99.dist-info/METADATA
DataPrep_Kit_khater-18.12.99.dist-info/WHEEL
DataPrep_Kit_khater-18.12.99.dist-info/license.txt
DataPrep_Kit_khater-18.12.99.dist-info/top_level.txt
DataPrep_Kit_khater-18.12.99.dist-info/RECORD
